<?xml version="1.0" encoding="UTF-8"?>
<data jsxnamespace="propsbundle">
  <locale key="zh">
    <record eval="1" jsxid="date.month.abbrev" jsxtext="['一月','二月','三月','四月','五月','六月','七月','八月','九月','十月','十一月','十二月']"/>
    <record eval="1" jsxid="date.month" jsxtext="['一月','二月','三月','四月','五月','六月','七月','八月','九月','十月','十一月','十二月']"/>
    <record eval="1" jsxid="date.month.narrow" jsxtext="['1月','2月','3月','4月','5月','6月','7月','8月','9月','10月','11月','12月']"/>
    <record eval="1" jsxid="date.day.abbrev" jsxtext="['周日','周一','周二','周三','周四','周五','周六']"/>
    <record eval="1" jsxid="date.day" jsxtext="['星期日','星期一','星期二','星期三','星期四','星期五','星期六']"/>
    <record eval="1" jsxid="date.day.narrow" jsxtext="['日','一','二','三','四','五','六']"/>
    <record eval="1" jsxid="date.era.long" jsxtext="['公元前','公元']"/>
    <record eval="1" jsxid="date.era" jsxtext="['公元前','公元']"/>
    <record eval="1" jsxid="time.ampm" jsxtext="['上午','下午']"/>
    <record jsxid="string.lang.ar" jsxtext="阿拉伯文"/>
    <record jsxid="string.lang.da" jsxtext="丹麦文"/>
    <record jsxid="string.lang.de" jsxtext="德文"/>
    <record jsxid="string.lang.el" jsxtext="希腊文"/>
    <record jsxid="string.lang.en" jsxtext="英文"/>
    <record jsxid="string.lang.es" jsxtext="西班牙文"/>
    <record jsxid="string.lang.fr" jsxtext="法文"/>
    <record jsxid="string.lang.it" jsxtext="意大利文"/>
    <record jsxid="string.lang.ja" jsxtext="日文"/>
    <record jsxid="string.lang.ko" jsxtext="韩文"/>
    <record jsxid="string.lang.pt" jsxtext="葡萄牙文"/>
    <record jsxid="string.lang.ru" jsxtext="俄文"/>
    <record jsxid="string.lang.sv" jsxtext="瑞典文"/>
    <record jsxid="string.lang.zh" jsxtext="中文"/>
    <record jsxid="string.terr.AU" jsxtext="澳大利亚"/>
    <record jsxid="string.terr.BR" jsxtext="巴西"/>
    <record jsxid="string.terr.CA" jsxtext="加拿大"/>
    <record jsxid="string.terr.CN" jsxtext="中国"/>
    <record jsxid="string.terr.DE" jsxtext="德国"/>
    <record jsxid="string.terr.DK" jsxtext="丹麦"/>
    <record jsxid="string.terr.ES" jsxtext="西班牙"/>
    <record jsxid="string.terr.FR" jsxtext="法国"/>
    <record jsxid="string.terr.GB" jsxtext="英国"/>
    <record jsxid="string.terr.GR" jsxtext="希腊"/>
    <record jsxid="string.terr.HK" jsxtext="中国香港特别行政区"/>
    <record jsxid="string.terr.IT" jsxtext="意大利"/>
    <record jsxid="string.terr.JP" jsxtext="日本"/>
    <record jsxid="string.terr.KR" jsxtext="韩国"/>
    <record jsxid="string.terr.MX" jsxtext="墨西哥"/>
    <record jsxid="string.terr.NZ" jsxtext="新西兰"/>
    <record jsxid="string.terr.PT" jsxtext="葡萄牙"/>
    <record jsxid="string.terr.RU" jsxtext="俄罗斯联邦"/>
    <record jsxid="string.terr.SE" jsxtext="瑞典"/>
    <record jsxid="string.terr.TW" jsxtext="台湾"/>
    <record jsxid="string.terr.US" jsxtext="美国"/>
  </locale>
<locale key="zh_CN">
    <record eval="1" jsxid="date.firstWeekDay" jsxtext="0"/>
    <record jsxid="currency.code" jsxtext="CNY"/>
  </locale>
<locale key="zh_HK">
    <record eval="1" jsxid="date.firstWeekDay" jsxtext="0"/>
    <record jsxid="currency.code" jsxtext="HKD"/>
  </locale>
<locale key="zh_TW">
    <record eval="1" jsxid="date.firstWeekDay" jsxtext="0"/>
    <record jsxid="currency.code" jsxtext="TWD"/>
  </locale>
</data>
