<?xml version="1.0"?>
<!DOCTYPE Configure PUBLIC "-//Mort Bay Consulting//DTD Configure//EN" "http://jetty.mortbay.org/configure.dtd">

<Configure id="Server" class="org.mortbay.jetty.Server">

  <Set name="stopAtShutdown">true</Set>
  <Set name="sendServerVersion">true</Set>
  <Set name="sendDateHeader">true</Set>
  <Set name="gracefulShutdown">1000</Set>

  <!-- Configure the NIO connector - why do I need to do more than the port? -->
  <Call name="addConnector">
    <Arg>
       <New class="org.mortbay.jetty.nio.SelectChannelConnector">
         <Set name="port">5380</Set>
         <Set name="maxIdleTime">30000</Set>
         <Set name="Acceptors">2</Set>
         <Set name="statsOn">false</Set>
         <Set name="lowResourcesConnections">5000</Set>
         <Set name="lowResourcesMaxIdleTime">5000</Set>
       </New>
    </Arg>
  </Call>

  <Set name="handler">
    <New id="Handlers" class="org.mortbay.jetty.handler.HandlerCollection">
      <Set name="handlers">
       <Array type="org.mortbay.jetty.Handler">
         <Item>
           <New id="Contexts" class="org.mortbay.jetty.handler.ContextHandlerCollection"/>
         </Item>
         <Item>
           <New id="DefaultHandler" class="org.mortbay.jetty.handler.DefaultHandler"/>
         </Item>
         <Item>
           <New id="RequestLog" class="org.mortbay.jetty.handler.RequestLogHandler"/>
         </Item>
       </Array>
      </Set>
    </New>
  </Set>

  <!-- Configure the context deployer -->
  <Call name="addLifeCycle">
    <Arg>
      <New class="org.mortbay.jetty.deployer.ContextDeployer">
        <Set name="contexts"><Ref id="Contexts"/></Set>
        <Set name="configurationDir"><SystemProperty name="jetty.home" default="."/>/contexts</Set>
        <Set name="scanInterval">1</Set>
      </New>
    </Arg>
  </Call>

</Configure>

  <!--
  <Set name="ThreadPool">
    The default is a BTP min=1, low=0, max=255
    <New class="org.mortbay.thread.BoundedThreadPool">
      <Set name="minThreads">10</Set>
      <Set name="maxThreads">250</Set>
      <Set name="lowThreads">25</Set>
    </New>
    <New class="org.mortbay.thread.concurrent.ThreadPool">
      <Set name="corePoolSize">250</Set>
      <Set name="maximumPoolSize">250</Set>
    </New>
  </Set>

  Took this out because we're not doing https
  <Call name="addConnector">
    <Arg>
       <New class="org.mortbay.jetty.nio.SelectChannelConnector">
         <Set name="confidentialPort">5343</Set>
       </New>
    </Arg>
  </Call>
  <Set name="sessionIdManager">
    <New class="org.mortbay.jetty.servlet.HashSessionIdManager">
      <Set name="workerName">node1</Set>
    </New>
  </Set>

  Configure Authentication Realms
  <Set name="UserRealms">
    <Array type="org.mortbay.jetty.security.UserRealm">
      <Item>
        <New class="org.mortbay.jetty.security.HashUserRealm">
          <Set name="name">Test Realm</Set>
          <Set name="config"><SystemProperty name="jetty.home" default="."/>/etc/realm.properties</Set>
        </New>
      </Item>
    </Array>
  </Set>
  -->
